setup.py
django_link_auth/__init__.py
django_link_auth/backends.py
django_link_auth/models.py
django_link_auth/settings.py
django_link_auth/signals.py
django_link_auth/test_urls.py
django_link_auth/tests.py
django_link_auth/urls.py
django_link_auth/utils.py
django_link_auth/views.py
django_link_auth.egg-info/PKG-INFO
django_link_auth.egg-info/SOURCES.txt
django_link_auth.egg-info/dependency_links.txt
django_link_auth.egg-info/not-zip-safe
django_link_auth.egg-info/top_level.txt