Metadata-Version: 1.0
Name: django-link-auth
Version: 0.1.0
Summary: Django's authentication backend to login by temporary URLs.
Home-page: http://github.com/svetlyak40wt/django-link-auth/
Author: Alexander Artemenko
Author-email: svetlyak.40wt@gmail.com
License: New BSD License
Keywords: django apps authentication
Platform: UNKNOWN
Classifier: Development Status :: 2 - Pre-Alpha
Classifier: Environment :: Plugins
Classifier: Framework :: Django
Classifier: Intended Audience :: Developers
Classifier: License :: OSI Approved :: BSD License
Classifier: Programming Language :: Python
Classifier: Topic :: Software Development :: Libraries :: Python Modules
